{"success": true, "message": "", "data": {"actasContabilizadas": 94.294, "contabilizadas": 87473, "totalActas": 92766, "participacionCiudadana": 69.745, "actasEnviadasJee": 5.637, "enviadasJee": 5229, "actasPendientesJee": 0.069, "pendientesJee": 64, "fechaActualizacion": 1776852000472, "idUbigeoDepartamento": 140000, "idUbigeoProvincia": 140100, "idUbigeoDistrito": 140101, "idUbigeoDistritoElectoral": 15, "totalVotosEmitidos": 19058038, "totalVotosValidos": 15880478, "porcentajeVotosEmitidos": 100, "porcentajeVotosValidos": 100}}